scPN/__init__.py
scPN/scPN_new.py
scpn-0.1.5.dist-info/METADATA
scpn-0.1.5.dist-info/WHEEL
scpn-0.1.5.dist-info/top_level.txt
scpn-0.1.5.dist-info/RECORD
