Metadata-Version: 2.4
Name: scPN
Version: 0.1.5
Summary: A package for single cell pseudotime
Home-page: https://github.com/ZHOUZHEN2002/scPN/tree/master
Author: Zhen Zhou
Author-email: zz20020101@sjtu.edu.cn
Classifier: Programming Language :: Python :: 3
Classifier: Operating System :: OS Independent
Requires-Python: >=3.7
Requires-Dist: numpy
Requires-Dist: scvelo
Requires-Dist: scanpy
Requires-Dist: numpy
Requires-Dist: scipy
Requires-Dist: torch
Requires-Dist: pandas
Requires-Dist: leidenalg
Requires-Dist: joblib
Dynamic: author
Dynamic: author-email
Dynamic: classifier
Dynamic: description
Dynamic: description-content-type
Dynamic: home-page
Dynamic: requires-dist
Dynamic: requires-python
Dynamic: summary
